libraries/templates/sw_reg_r/sw_reg_r.v
//============================================================================//
//                                                                            //
//      Software Register with bus read only                                  //
//                                                                            //
//      Module name: sw_reg_r                                                 //
//      Desc: software register with wishbone bus inferface read only and     //
//            write only from fabric interface                                //
//      Date: Dec 2011                                                        //
//      Developer: Wesley New                                                 //
//      Licence: GNU General Public License ver 3                             //
//      Notes: To avoid race conditions the software reg is split into 2      //
//             different modules                                              //
//                                                                            //
//============================================================================//
//                               _________                                    //
//                         read |         | write                             //
//                     SW <-----|   Reg   |<----- Fabric                      //
//                              |_________|                                   //
//                                                                            //
//============================================================================//

module sw_reg_r #(
      //=============
      // parameters
      //=============
      parameter DEV_BASE_ADDR  = {BUS_ADDR_WIDTH{1'b0}}, // default 32'h0
      parameter DEV_HIGH_ADDR  = {{(BUS_ADDR_WIDTH-4){1'b0}}, 4'hF}, // default 32'h000000EE
      parameter BUS_DATA_WIDTH = 32,  // default is 32. but can be 8, 16, 32, 64
      parameter BUS_ADDR_WIDTH = 8    // default is 8.  but can be 4, 8, 16, 32
   ) (
      //===============
      // fabric ports
      //===============
      input        fabric_clk_i,
      input [31:0] fabric_data_i,
      
      //============
      // wb inputs
      //============
      input                      wb_clk_i,
      input                      wb_rst_i,
      input                      wbs_cyc_i,
      input                      wbs_stb_i,
      input                      wbs_we_i,
      input   [BYTE_ENABLES-1:0] wbs_sel_i,
      input [BUS_ADDR_WIDTH-1:0] wbs_adr_i,
      input [BUS_DATA_WIDTH-1:0] wbs_dat_i,
      
      //=============
      // wb outputs
      //=============
      output reg [BUS_DATA_WIDTH-1:0] wbs_dat_o,
      output reg                      wbs_ack_o,
      output reg                      wbs_err_o,
      output reg                      wbs_int_o
   );
   
   //===================
   // local parameters
   //===================
   // byte enable is always the data width/8
   // thus the data width is only able to be multiples of 8
   localparam BYTE_ENABLES = BUS_DATA_WIDTH / 8;
   
   //========
   // wires
   //========
   wire adr_match = wbs_adr_i >= DEV_BASE_ADDR && wbs_adr_i <= DEV_HIGH_ADDR;

   //============
   // registers
   //============
   reg [BUS_DATA_WIDTH-1:0] fabric_data_i_reg;
   reg [BUS_DATA_WIDTH-1:0] wbs_dat_o_reg;
   reg [BUS_DATA_WIDTH-1:0] reg_buf = {BUS_DATA_WIDTH{1'b0}};

   // Handshake signal from WB to application indicating data is ready to be latched
   reg register_ready;
   reg register_readyR;
   reg register_readyRR;
   // Handshake signal from application to WB indicating data has been latched
   reg register_request;
   reg register_requestR;
   reg register_requestRR;

   //===============
   // fabric logic
   //===============
   always @(posedge fabric_clk_i)
   begin
      // registering for clock domain crossing  
      register_requestR  <= register_request;
      register_requestRR <= register_requestR;

      if (register_requestRR)
      begin
         register_ready <= 1'b1;
      end

      if (!register_requestRR)
      begin
         register_ready <= 1'b0;
      end
      if (register_requestRR && !register_ready)
      begin
         register_ready <= 1'b1;
         fabric_data_i_reg = fabric_data_i;
         //$display("fabric data read %h", fabric_data_i);
      end
   end

   //=================
   // wishbone logic
   //=================
   always @ (posedge wb_clk_i) begin
      register_readyR  <= register_ready;
      register_readyRR <= register_readyR;
     
      if (register_readyRR) begin
         register_request <= 1'b0;
      end

      if (register_readyRR && register_request) begin
         /* only latch the data when the buffer is not locked */
         reg_buf <= fabric_data_i_reg;
      end

      if (!register_readyRR) begin
         /* always request the buffer */
         register_request <= 1'b1;
      end

      // reset logic 
      if (wb_rst_i) begin
         wbs_ack_o <= 0;
         wbs_err_o <= 0;
         wbs_int_o <= 0;
         register_request <= 1'b0;
      end
      else begin
         // when the master acks our ack, then put our ack down
         if (wbs_ack_o & ~wbs_stb_i) begin
            wbs_ack_o <= 0;
         end
         // master is requesting somethign
         if (adr_match & wbs_stb_i & wbs_cyc_i) begin
            wbs_dat_o <= wbs_dat_o_reg;
            //===============
            // read request
            //===============
            if (~wbs_we_i)
            begin 
               case (wbs_adr_i - DEV_BASE_ADDR)
                  32'h0: begin
                     //reading something from address 0
                     //$display("user read %h", reg_buf);
                     wbs_dat_o_reg <= reg_buf;
                  end
                  //add as many addresses as you need here
                  default: begin
                     //$display("no case for read address %h", wbs_adr_i);
                  end
               endcase
            end
            wbs_ack_o <= 1;
         end
         // if not (adr_match, wbs_cyc_i or wb_stb_i) release the Kraken!... I mean the data_o port
         else
            wbs_dat_o = 32'bz;
      end
   end
endmodule

libraries/controllers/sw_reg/sw_reg_r_tb.v
//============================================================================//
//                                                                            //
//      Software Reg test bench                                               //
//                                                                            //
//      Module name: sw_reg_tb                                                //
//      Desc: runs and tests the sw_reg module, and provides and interface    //
//            to test the module from Python (MyHDL)                          //
//      Date: Dec 2011                                                        //
//      Developer: Wesley New                                                 //
//      Licence: GNU General Public License ver 3                             //
//      Notes: This only tests the basic functionality of the module, more    //
//             comprehensive testing is done in the python test file          //
//                                                                            //
//============================================================================//

module sw_reg_r_tb;
   
   //===================
   // local parameters
   //===================
   localparam BUS_DATA_WIDTH = 32;  // 8, 16, 32, 64
   localparam BUS_ADDR_WIDTH = 8;   // 4, 8, 16, 32
   localparam DEV_BASE_ADDR  = 32'h0;
   localparam DEV_HIGH_ADDR  = 8'h0F;
   localparam BYTE_EN_WIDTH  = BUS_DATA_WIDTH / 8;

   //=====================
   // local wires & regs
   //=====================
   reg                       wb_clk_i;
   reg                       wb_rst_i;
   reg                       wbs_cyc_i;
   reg                       wbs_stb_i;
   reg                       wbs_we_i;
   reg   [BYTE_EN_WIDTH-1:0] wbs_sel_i;
   reg  [BUS_ADDR_WIDTH-1:0] wbs_adr_i;
   reg  [BUS_DATA_WIDTH-1:0] wbs_dat_i;
   wire [BUS_DATA_WIDTH-1:0] wbs_dat_o;
   wire                      wbs_ack_o;
   wire                      wbs_int_o;

   reg                       fabric_clk_i;
   reg  [BUS_DATA_WIDTH-1:0] fabric_data_i;

   //=====================================
   // instance, "(d)esign (u)nder (t)est"
   //=====================================
   sw_reg_r #(
      .DEV_BASE_ADDR  (DEV_BASE_ADDR),
      .DEV_HIGH_ADDR  (DEV_HIGH_ADDR),
      .BUS_DATA_WIDTH (BUS_DATA_WIDTH),
      .BUS_ADDR_WIDTH (BUS_ADDR_WIDTH)
   ) dut (
      .fabric_clk_i  (fabric_clk_i),
      .fabric_data_i (fabric_data_i),
      
      .wb_clk_i  (wb_clk_i),
      .wb_rst_i  (wb_rst_i),
      .wbs_cyc_i (wbs_cyc_i),
      .wbs_stb_i (wbs_stb_i),
      .wbs_we_i  (wbs_we_i),
      .wbs_sel_i (wbs_sel_i),
      .wbs_adr_i (wbs_adr_i),
      .wbs_dat_i (wbs_dat_i),
      .wbs_dat_o (wbs_dat_o),
      .wbs_ack_o (wbs_ack_o),
      .wbs_int_o (wbs_int_o)
   );

//==============
// MyHDL hooks
//==============
`ifdef MYHDL
   // define what myhdl takes over
   // only if we're running myhdl   
   initial begin
      $from_myhdl(fabric_clk_i, fabric_data_o, wb_clk_i, wb_rst_i, wb_cyc_i, wb_stb_i, wb_we_i, wb_sel_i, wb_adr_i, wb_dat_i);
      $to_myhdl(wb_dat_o,wb_ack_o,wb_err_o);
   end
`else

   //==============
   // Initialize
   //==============
   initial
      begin
         $dumpvars;

         fabric_clk_i = 0;

         fabric_data_i = 32'hEEEEEEEE;

         #5

         // read from device 
         wb_clk_i  = 0;
         wb_rst_i  = 1;
         wbs_sel_i = 4'hA;
         wbs_stb_i = 0;
         wbs_cyc_i = 0;
         wbs_we_i  = 0;
         wbs_adr_i = 8'h00;

         #2 

         wb_rst_i  = 0;

         #25
         
         // read from device
         wbs_adr_i = 8'h00;
         wbs_stb_i = 1;
         wbs_cyc_i = 1;
         wbs_we_i  = 0;

         #5
         
         if (wbs_dat_o == 32'hEEEEEEEE) begin
            $display("PASSES: Fabric write or wishbone read");
         end
         else
            $display("Failed: Fabric write or wishbone read");
         
         wbs_stb_i = 0;

         $finish;
      end

   //=====================
   // Simulate the Clock
   //=====================
   always #1
   begin
      wb_clk_i     = ~wb_clk_i;
      fabric_clk_i = ~fabric_clk_i;
   end

`endif

endmodule

libraries/templates/sw_reg_r/gen/dump.vcd
$date
	Mon Jul  9 09:19:04 2012
$end
$version
	Icarus Verilog
$end
$timescale
	1s
$end
$scope module sw_reg_r_tb $end
$var wire 1 ! wbs_ack_o $end
$var wire 32 " wbs_dat_o [31:0] $end
$var wire 1 # wbs_int_o $end
$var reg 1 $ fabric_clk_i $end
$var reg 32 % fabric_data_i [31:0] $end
$var reg 1 & wb_clk_i $end
$var reg 1 ' wb_rst_i $end
$var reg 8 ( wbs_adr_i [7:0] $end
$var reg 1 ) wbs_cyc_i $end
$var reg 32 * wbs_dat_i [31:0] $end
$var reg 4 + wbs_sel_i [3:0] $end
$var reg 1 , wbs_stb_i $end
$var reg 1 - wbs_we_i $end
$scope module dut $end
$var wire 1 . adr_match $end
$var wire 1 / fabric_clk_i $end
$var wire 32 0 fabric_data_i [31:0] $end
$var wire 1 1 wb_clk_i $end
$var wire 1 2 wb_rst_i $end
$var wire 8 3 wbs_adr_i [7:0] $end
$var wire 1 4 wbs_cyc_i $end
$var wire 32 5 wbs_dat_i [31:0] $end
$var wire 4 6 wbs_sel_i [3:0] $end
$var wire 1 7 wbs_stb_i $end
$var wire 1 8 wbs_we_i $end
$var reg 32 9 fabric_data_i_reg [31:0] $end
$var reg 32 : reg_buf [31:0] $end
$var reg 1 ; register_ready $end
$var reg 1 < register_readyR $end
$var reg 1 = register_readyRR $end
$var reg 1 > register_request $end
$var reg 1 ? register_requestR $end
$var reg 1 @ register_requestRR $end
$var reg 1 A wbs_ack_o $end
$var reg 32 B wbs_dat_o [31:0] $end
$var reg 32 C wbs_dat_o_reg [31:0] $end
$var reg 1 D wbs_err_o $end
$var reg 1 E wbs_int_o $end
$upscope $end
$upscope $end
$enddefinitions $end
#0
$dumpvars
xE
xD
bx C
bx B
xA
x@
x?
x>
x=
x<
x;
b0 :
bx 9
x8
x7
bx 6
bx 5
x4
bx 3
x2
x1
b11101110111011101110111011101110 0
0/
x.
x-
x,
bx +
bx *
x)
bx (
x'
x&
b11101110111011101110111011101110 %
0$
x#
bx "
x!
$end
#1
1$
1/
#2
0$
0/
#3
1$
1/
#4
0$
0/
#5
0>
0E
0#
0D
0A
0!
1.
1$
1/
b0 (
b0 3
0-
08
0)
04
0,
07
b1010 +
b1010 6
1'
12
1&
11
#6
0$
0/
0&
01
#7
0?
bz B
bz "
1$
1/
1&
11
0'
02
#8
0$
0/
0&
01
#9
0@
1$
1/
1&
11
#10
0$
0/
0&
01
#11
0;
1$
1/
1&
11
#12
0$
0/
0&
01
#13
0<
1$
1/
1&
11
#14
0$
0/
0&
01
#15
0=
1$
1/
1&
11
#16
0$
0/
0&
01
#17
1>
1$
1/
1&
11
#18
0$
0/
0&
01
#19
1?
1$
1/
1&
11
#20
0$
0/
0&
01
#21
1@
1$
1/
1&
11
#22
0$
0/
0&
01
#23
1;
b11101110111011101110111011101110 9
1$
1/
1&
11
#24
0$
0/
0&
01
#25
1<
1$
1/
1&
11
#26
0$
0/
0&
01
#27
1=
1$
1/
1&
11
#28
0$
0/
0&
01
#29
b11101110111011101110111011101110 :
0>
1$
1/
1&
11
#30
0$
0/
0&
01
#31
0?
1$
1/
1&
11
#32
0$
0/
0&
01
1)
14
1,
17
#33
0@
1A
1!
b11101110111011101110111011101110 C
bx B
bx "
1$
1/
1&
11
#34
0$
0/
0&
01
#35
0;
b11101110111011101110111011101110 B
b11101110111011101110111011101110 "
1$
1/
1&
11
#36
0$
0/
0&
01
#37
0A
0!
0<
bz B
bz "
1$
1/
1&
11
0,
07
