libraries/templates/sw_reg_wr/sw_reg_wr.v
//============================================================================//
//                                                                            //
//      Parameterize Wishbone Slave Template                                  //
//                                                                            //
//      Module name: wbs_template                                             //
//      Desc: parameterized wishbone slave template, with byte enables and    //
//            parameterized address and data widths.                          //
//      Date: July 2012                                                       //
//      Developer: Wesley New                                                 //
//      Licence: GNU General Public License ver 3                             //
//      Notes:                                                                //
//                                                                            //
//============================================================================//

module sw_reg_wr #(
      //=============
      // parameters
      //=============
      parameter DEV_BASE_ADDR  = {BUS_ADDR_WIDTH{1'b0}}, // default 32'h0
      parameter DEV_HIGH_ADDR  = {{(BUS_ADDR_WIDTH-4){1'b0}}, 4'hF}, // default 32'h000000EE
      parameter BUS_DATA_WIDTH = 32,  // default is 32. but can be 8, 16, 32, 64
      parameter BUS_ADDR_WIDTH = 8    // default is 8.  but can be 4, 8, 16, 32
   ) (
      //===============
      // fabric ports
      //===============
      input         fabric_clk_i,
      output [31:0] fabric_data_o,
      
      //============
      // wb inputs
      //============
      input                      wb_clk_i,
      input                      wb_rst_i,
      input                      wbs_cyc_i,
      input                      wbs_stb_i,
      input                      wbs_we_i,
      input   [BYTE_ENABLES-1:0] wbs_sel_i,
      input [BUS_ADDR_WIDTH-1:0] wbs_adr_i,
      input [BUS_DATA_WIDTH-1:0] wbs_dat_i,
      
      //=============
      // wb outputs
      //=============
      output reg [BUS_DATA_WIDTH-1:0] wbs_dat_o,
      output reg                      wbs_ack_o,
      output reg                      wbs_err_o,
      output reg                      wbs_int_o
   );

   integer i;

   //===================
   // local parameters
   //===================
   // byte enable is always the data width/8
   // thus the data width is only able to be multiples of 8
   localparam BYTE_ENABLES = BUS_DATA_WIDTH / 8;
   
   //========
   // wires
   //========
   wire adr_match = wbs_adr_i >= DEV_BASE_ADDR && wbs_adr_i <= DEV_HIGH_ADDR;

   //============
   // registers
   //============
   reg [BUS_DATA_WIDTH-1:0] fabric_data_o_reg;
   reg [BUS_DATA_WIDTH-1:0] wbs_dat_o_reg;
   reg [BUS_DATA_WIDTH-1:0] reg_buf = {BUS_DATA_WIDTH{1'b0}};

   // Handshake signal from WB to application indicating data is ready to be latched
   reg register_ready;
   reg register_readyR;
   reg register_readyRR;
   // Handshake signal from application to WB indicating data has been latched
   reg register_done;
   reg register_doneR;
   reg register_doneRR;

   assign fabric_data_o = fabric_data_o_reg;

   //===============
   // fabric logic
   //===============
   always @(posedge fabric_clk_i)
   begin
      // registering for clock domain crossing  
      register_readyR  <= register_ready;
      register_readyRR <= register_readyR;

      if (!register_readyRR)
      begin
         register_done <= 1'b0;
      end

      if (register_readyRR)
      begin
         register_done <= 1'b1;
         fabric_data_o_reg <= reg_buf;
         //$display("fabric data read %h", fabric_data_o);
      end
   end

   //=================
   // wishbone logic
   //=================
   always @ (posedge wb_clk_i) begin
      register_doneR  <= register_done;
      register_doneRR <= register_doneR;
      // reset logic
      if (register_doneRR)
      begin
         register_ready <= 1'b0;
      end
      
     if (wb_rst_i) begin
         wbs_ack_o <= 0;
         wbs_err_o <= 0;
         wbs_int_o <= 0;
         register_ready <= 1'b0;
      end
      else begin
         // when the master acks our ack, then put our ack down
         if (wbs_ack_o & ~wbs_stb_i) begin
            wbs_ack_o <= 0;
         end
         // master is requesting somethign
         if (adr_match & wbs_stb_i & wbs_cyc_i) begin
            wbs_dat_o <= wbs_dat_o_reg;
            //================
            // write request
            //================
            if (wbs_we_i) begin
               register_ready <= 1'b1;
               // bring the address down to the base address
               case (wbs_adr_i - DEV_BASE_ADDR)
                  // writing something to address
                  32'h0: begin
                     // byte enabled writes, depending on the data width of the bus
                     // this isnt able to be done with generate statements as
                     // cant be used inside always blocks. BLAH!
                     // these take into account a possible data width of up to 64 bits
                     if (BYTE_ENABLES >= 1)
                        if (wbs_sel_i[0])
                           reg_buf  [7:0] <= wbs_dat_i[7:0];
                     if (BYTE_ENABLES >= 2)
                        if (wbs_sel_i[1])
                           reg_buf [15:8] <= wbs_dat_i[15:8];
                     if (BYTE_ENABLES >= 3)
                        if (wbs_sel_i[2])
                           reg_buf[23:16] <= wbs_dat_i[23:16];
                     if (BYTE_ENABLES >= 4)
                        if (wbs_sel_i[3])
                           reg_buf[31:24] <= wbs_dat_i[31:24];
                     if (BYTE_ENABLES >= 5)
                        if (wbs_sel_i[4])
                           reg_buf[39:32] <= wbs_dat_i[39:32];
                     if (BYTE_ENABLES >= 6)
                        if (wbs_sel_i[5])
                           reg_buf[47:40] <= wbs_dat_i[47:40];
                     if (BYTE_ENABLES >= 7)
                        if (wbs_sel_i[6])
                           reg_buf[55:48] <= wbs_dat_i[55:48];
                     if (BYTE_ENABLES >= 8)
                        if (wbs_sel_i[7])
                           reg_buf[63:56] <= wbs_dat_i[63:56];
                     
                     //$display("user wrote %h", reg_buf);
                  end
                  //add as many addresses as you need here
                  default: begin
                     //$display("no case for write address %h", wbs_adr_i);
                  end
               endcase
            end
            
            //===============
            // read request
            //===============
            else begin 
               case (wbs_adr_i - DEV_BASE_ADDR)
                  32'h0: begin
                     //reading something from address 0
                     //$display("user read %h", reg_buf);
                     wbs_dat_o_reg <= reg_buf;
                  end
                  //add as many addresses as you need here
                  default: begin
                     //$display("no case for read address %h", wbs_adr_i);
                  end
               endcase
            end
            wbs_ack_o <= 1;
         end
         // if not (adr_match, wbs_cyc_i or wb_stb_i) release the Kraken!... I mean the data_o port
         else
            wbs_dat_o = 32'bz;
      end
   end
endmodule

libraries/templates/sw_reg_wr/sw_reg_wr_tb.v
//============================================================================//
//                                                                            //
//      Wishbone slave template test bench                                    //
//                                                                            //
//      Module name: bram_wb_tb                                               //
//      Desc: runs and tests the wbs_template module,                         //
//      Date: Jule 2012                                                       //
//      Developer: Wesley New                                                 //
//      Licence: GNU General Public License ver 3                             //
//      Notes:                                                                //
//                                                                            //
//============================================================================//

module sw_reg_wr_tb;

   localparam BUS_DATA_WIDTH = 32;  // 8, 16, 32, 64
   localparam BUS_ADDR_WIDTH = 8;   // 4, 8, 16, 32
   localparam DEV_BASE_ADDR  = 32'h0;
   localparam DEV_HIGH_ADDR  = 8'h0F;
   localparam BYTE_EN_WIDTH  = BUS_DATA_WIDTH / 8;

   //=====================
   // local wires & regs
   //=====================
   reg                       wb_clk_i;
   reg                       wb_rst_i;
   reg                       wbs_cyc_i;
   reg                       wbs_stb_i;
   reg                       wbs_we_i;
   reg   [BYTE_EN_WIDTH-1:0] wbs_sel_i;
   reg  [BUS_ADDR_WIDTH-1:0] wbs_adr_i;
   reg  [BUS_DATA_WIDTH-1:0] wbs_dat_i;
   wire [BUS_DATA_WIDTH-1:0] wbs_dat_o;
   wire                      wbs_ack_o;
   wire                      wbs_int_o;

   reg                       fabric_clk_i;
   wire [BUS_DATA_WIDTH-1:0] fabric_data_o;

   //=====================================
   // instance, "(d)esign (u)nder (t)est"
   //=====================================
   sw_reg_wr #(
      .DEV_BASE_ADDR  (DEV_BASE_ADDR),
      .DEV_HIGH_ADDR  (DEV_HIGH_ADDR),
      .BUS_DATA_WIDTH (BUS_DATA_WIDTH),
      .BUS_ADDR_WIDTH (BUS_ADDR_WIDTH)
   ) dut (
      .fabric_clk_i  (fabric_clk_i),
      .fabric_data_o (fabric_data_o),
      
      .wb_clk_i  (wb_clk_i),
      .wb_rst_i  (wb_rst_i),
      .wbs_cyc_i (wbs_cyc_i),
      .wbs_stb_i (wbs_stb_i),
      .wbs_we_i  (wbs_we_i),
      .wbs_sel_i (wbs_sel_i),
      .wbs_adr_i (wbs_adr_i),
      .wbs_dat_i (wbs_dat_i),
      .wbs_dat_o (wbs_dat_o),
      .wbs_ack_o (wbs_ack_o),
      .wbs_int_o (wbs_int_o)
   );

//==============
// MyHDL hooks
//==============
`ifdef MYHDL
   // define what myhdl takes over
   // only if we're running myhdl   
   initial begin
      $from_myhdl(fabric_clk_i, fabric_data_o, wb_clk_i, wb_rst_i, wb_cyc_i, wb_stb_i, wb_we_i, wb_sel_i, wb_adr_i, wb_dat_i);
      $to_myhdl(wb_dat_o,wb_ack_o,wb_err_o);
   end
`else

   //==============
   // Initialize
   //==============
   initial
      begin
         $dumpvars;

         fabric_clk_i = 0;

         // write to device 
         wb_clk_i  = 0;
         wb_rst_i  = 1;
         wbs_sel_i = 4'hA;
         wbs_stb_i = 1;
         wbs_cyc_i = 1;
         wbs_we_i  = 1;
         wbs_adr_i = 8'h00;
         wbs_dat_i = 32'hEEEEEEEE;

         #2 

         wb_rst_i  = 0;

         #5

         wbs_stb_i = 0;
         wbs_cyc_i = 0;

         #5
         
         // read from device
         wbs_adr_i = 8'h00;
         wbs_stb_i = 1;
         wbs_cyc_i = 1;
         wbs_we_i  = 0;

         #5
         
         wbs_stb_i = 0;

         if (wbs_dat_o == 32'hEE00EE00) begin
            $display("PASSES: Wishbone write with byte enable");
            $display("PASSED: Wishbone read");
         end
         else
            $display("Failed: Wishbone read or write");
         if (fabric_data_o == 32'hEE00EE00)
            $display("PASSED: Fabric read");
         else
            $display("Failed: Fabric read");

         #20 $finish;
      end

   //=====================
   // Simulate the Clock
   //=====================
   always #1
   begin
      wb_clk_i     = ~wb_clk_i;
      fabric_clk_i = ~fabric_clk_i;
   end

`endif

endmodule

libraries/templates/sw_reg_wr/gen/dump.vcd
$date
	Mon Jul  9 09:18:22 2012
$end
$version
	Icarus Verilog
$end
$timescale
	1s
$end
$scope module sw_reg_wr_tb $end
$var wire 32 ! fabric_data_o [31:0] $end
$var wire 1 " wbs_ack_o $end
$var wire 32 # wbs_dat_o [31:0] $end
$var wire 1 $ wbs_int_o $end
$var reg 1 % fabric_clk_i $end
$var reg 1 & wb_clk_i $end
$var reg 1 ' wb_rst_i $end
$var reg 8 ( wbs_adr_i [7:0] $end
$var reg 1 ) wbs_cyc_i $end
$var reg 32 * wbs_dat_i [31:0] $end
$var reg 4 + wbs_sel_i [3:0] $end
$var reg 1 , wbs_stb_i $end
$var reg 1 - wbs_we_i $end
$scope module dut $end
$var wire 1 . adr_match $end
$var wire 1 / fabric_clk_i $end
$var wire 32 0 fabric_data_o [31:0] $end
$var wire 1 1 wb_clk_i $end
$var wire 1 2 wb_rst_i $end
$var wire 8 3 wbs_adr_i [7:0] $end
$var wire 1 4 wbs_cyc_i $end
$var wire 32 5 wbs_dat_i [31:0] $end
$var wire 4 6 wbs_sel_i [3:0] $end
$var wire 1 7 wbs_stb_i $end
$var wire 1 8 wbs_we_i $end
$var reg 32 9 fabric_data_o_reg [31:0] $end
$var reg 32 : reg_buf [31:0] $end
$var reg 1 ; register_done $end
$var reg 1 < register_doneR $end
$var reg 1 = register_doneRR $end
$var reg 1 > register_ready $end
$var reg 1 ? register_readyR $end
$var reg 1 @ register_readyRR $end
$var reg 1 A wbs_ack_o $end
$var reg 32 B wbs_dat_o [31:0] $end
$var reg 32 C wbs_dat_o_reg [31:0] $end
$var reg 1 D wbs_err_o $end
$var reg 1 E wbs_int_o $end
$upscope $end
$upscope $end
$enddefinitions $end
#0
$dumpvars
xE
xD
bx C
bx B
xA
x@
x?
x>
x=
x<
x;
b0 :
bx 9
18
17
b1010 6
b11101110111011101110111011101110 5
14
b0 3
12
01
bx 0
0/
1.
1-
1,
b1010 +
b11101110111011101110111011101110 *
1)
b0 (
1'
0&
0%
x$
bx #
x"
bx !
$end
#1
0>
0E
0$
0D
0A
0"
1%
1/
1&
11
#2
0%
0/
0&
01
0'
02
#3
0?
1A
1"
b11101110000000001110111000000000 :
1>
1%
1/
1&
11
#4
0%
0/
0&
01
#5
0@
1?
b11101110000000001110111000000000 :
1%
1/
1&
11
#6
0%
0/
0&
01
#7
0;
1@
0A
0"
bz B
bz #
1%
1/
1&
11
0)
04
0,
07
#8
0%
0/
0&
01
#9
b11101110000000001110111000000000 9
b11101110000000001110111000000000 !
b11101110000000001110111000000000 0
1;
0<
1%
1/
1&
11
#10
0%
0/
0&
01
#11
0=
1<
1%
1/
1&
11
#12
0%
0/
0&
01
0-
08
1)
14
1,
17
#13
1A
1"
b11101110000000001110111000000000 C
bx B
bx #
1=
1%
1/
1&
11
#14
0%
0/
0&
01
#15
b11101110000000001110111000000000 B
b11101110000000001110111000000000 #
0>
1%
1/
1&
11
#16
0%
0/
0&
01
#17
0?
0A
0"
bz B
bz #
1%
1/
1&
11
0,
07
#18
0%
0/
0&
01
#19
0@
1%
1/
1&
11
#20
0%
0/
0&
01
#21
0;
1%
1/
1&
11
#22
0%
0/
0&
01
#23
0<
1%
1/
1&
11
#24
0%
0/
0&
01
#25
0=
1%
1/
1&
11
