libraries/dev_modules/edge_detect/verilog/edge_detect.v
//============================================================================//
//                                                                            //
//      Edge Detect                                                           //
//                                                                            //
//      Module name: edge_detect                                              //
//      Desc: runs and tests the counter module, and provides and interface   //
//            to test the module from Python (MyHDL)                          //
//      Date: Oct 2011                                                        //
//      Developer: Rurik Primiani & Wesley New                                //
//      Licence: GNU General Public License ver 3                             //
//      Notes: This only tests the basic functionality of the module, more    //
//             comprehensive testing is done in the python test file          //
//                                                                            //
//============================================================================//

module edge_detect #(

      //===================
      // local parameters
      //===================
      parameter DATA_WIDTH = 8,
      parameter EDGE_TYPE  = "RISE"
   ) (
      //=============
      // local regs
      //=============
      input clk,
      input en,
      input [DATA_WIDTH-1:0] in,
      
      //==============
      // local wires
      //==============
      output [DATA_WIDTH-1:0] pulse_out
   );

   reg [DATA_WIDTH-1:0] delay_reg;
   reg [DATA_WIDTH-1:0] delay_reg1;

   always@(posedge clk) begin
      delay_reg  <= in;
      delay_reg1 <= delay_reg;
   end

   case (EDGE_TYPE)
      "RISE" : assign pulse_out =  in & ~delay_reg1;
      "FALL" : assign pulse_out = ~in &  delay_reg1;
      "DUAL" : assign pulse_out =  in ^  delay_reg1;
      defaut : assign pulse_out =  in & ~delay_reg1; 
   endcase
        


endmodule

libraries/dev_modules/edge_detect/edge_detect_tb.v
//============================================================================//
//                                                                            //
//      Counter test bench                                                    //
//                                                                            //
//      Module name: counter_tb                                               //
//      Desc: runs and tests the counter module, and provides and interface   //
//            to test the module from Python (MyHDL)                          //
//      Date: Oct 2011                                                        //
//      Developer: Rurik Primiani & Wesley New                                //
//      Licence: GNU General Public License ver 3                             //
//      Notes: This only tests the basic functionality of the module, more    //
//             comprehensive testing is done in the python test file          //
//                                                                            //
//============================================================================//

module edge_detect_tb;

   //===================
   // local parameters
   //===================
   localparam LOCAL_DATA_WIDTH = 8'h8;
   localparam LOCAL_EDGE_TYPE  = "RISE";

   //=============
   // local regs
   //=============
   reg clk;
   reg en;
   reg [LOCAL_DATA_WIDTH-1:0] in;
   
   //==============
   // local wires
   //==============
   wire [LOCAL_DATA_WIDTH-1:0] out;

   //=====================================
   // instance, "(d)esign (u)nder (t)est"
   //=====================================
   edge_detect #(
      .DATA_WIDTH (LOCAL_DATA_WIDTH),
      .EDGE_TYPE  (LOCAL_EDGE_TYPE)
   ) dut (
      .clk       (clk), 
      .en        (en), 
      .in        (in), 
      .pulse_out (out)
   );

   
   //=============
   // initialize
   //=============
   initial
   begin
      $dumpvars;
      clk = 1'b0;
      en  = 1'b1;
      in  = 8'b10101010;
      #5
      in  = 8'b01010101;
      #5
      in  = 8'b11110000;
      #5
      in  = 8'b00001111;
   end

   //====================
   // simulate the clock
   //====================
   always #1
   begin
      clk = ~clk;
   end

   //===============
   // print output
   //===============
   always @(negedge clk) $display(out);
   
   //===============================
   // finish after 100 clock cycles
   //===============================
   initial #20 $finish;

endmodule

libraries/dev_modules/edge_detect/verilog/dump.vcd
$date
	Mon Feb 24 13:16:08 2014
$end
$version
	Icarus Verilog
$end
$timescale
	1s
$end
$scope module edge_detect_tb $end
$var wire 8 ! out [7:0] $end
$var reg 1 " clk $end
$var reg 1 # en $end
$var reg 8 $ in [7:0] $end
$scope module dut $end
$var wire 1 % clk $end
$var wire 1 & en $end
$var wire 8 ' in [7:0] $end
$var wire 8 ( pulse_out [7:0] $end
$var reg 8 ) delay_reg [7:0] $end
$var reg 8 * delay_reg1 [7:0] $end
$scope begin genblk1 $end
$upscope $end
$upscope $end
$upscope $end
$enddefinitions $end
#0
$dumpvars
bx *
bx )
bx (
b10101010 '
1&
0%
b10101010 $
1#
0"
bx !
$end
#1
b10101010 )
1"
1%
#2
0"
0%
#3
b0 !
b0 (
b10101010 *
1"
1%
#4
0"
0%
#5
b1010101 )
b11111111 !
b11111111 (
1"
1%
b1010101 $
b1010101 '
#6
0"
0%
#7
b0 !
b0 (
b1010101 *
1"
1%
#8
0"
0%
#9
1"
1%
#10
b10100101 !
b10100101 (
0"
0%
b11110000 $
b11110000 '
#11
b11110000 )
1"
1%
#12
0"
0%
#13
b0 !
b0 (
b11110000 *
1"
1%
#14
0"
0%
#15
b1111 )
b11111111 !
b11111111 (
1"
1%
b1111 $
b1111 '
#16
0"
0%
#17
b0 !
b0 (
b1111 *
1"
1%
